sipher_package/__init__.py
sipher_package/cli.py
sipher_package/cipher_code/aes/client.py
sipher_package/cipher_code/aes/server.py
sipher_package/cipher_code/caesar/client.py
sipher_package/cipher_code/caesar/server.py
sipher_package/cipher_code/des/client.py
sipher_package/cipher_code/des/server.py
sipher_package/cipher_code/diffie/client.py
sipher_package/cipher_code/diffie/server.py
sipher_package/cipher_code/dss/client.py
sipher_package/cipher_code/dss/server.py
sipher_package/cipher_code/hill/client.py
sipher_package/cipher_code/hill/server.py
sipher_package/cipher_code/hmac/client.py
sipher_package/cipher_code/hmac/server.py
sipher_package/cipher_code/hmac2/client.py
sipher_package/cipher_code/hmac2/server.py
sipher_package/cipher_code/mdfive/client.py
sipher_package/cipher_code/mdfive/server.py
sipher_package/cipher_code/mdfive2/client.py
sipher_package/cipher_code/mdfive2/server.py
sipher_package/cipher_code/monoalphabetic/client.py
sipher_package/cipher_code/monoalphabetic/server.py
sipher_package/cipher_code/onetimepad/client.py
sipher_package/cipher_code/onetimepad/server.py
sipher_package/cipher_code/playfair/client.py
sipher_package/cipher_code/playfair/server.py
sipher_package/cipher_code/railfence/client.py
sipher_package/cipher_code/railfence/server.py
sipher_package/cipher_code/rsa/client.py
sipher_package/cipher_code/rsa/server.py
sipher_package/cipher_code/sha/client.py
sipher_package/cipher_code/sha/server.py
sipher_package/cipher_code/sha512/client.py
sipher_package/cipher_code/sha512/server.py
sipher_package/cipher_code/something/client.py
sipher_package/cipher_code/something/server.py
sipher_package/cipher_code/vernam/client.py
sipher_package/cipher_code/vernam/server.py
sipher_package/cipher_code/vigenere/client.py
sipher_package/cipher_code/vigenere/server.py
sipher_lab-0.1.5.dist-info/METADATA
sipher_lab-0.1.5.dist-info/WHEEL
sipher_lab-0.1.5.dist-info/entry_points.txt
sipher_lab-0.1.5.dist-info/top_level.txt
sipher_lab-0.1.5.dist-info/RECORD
