Metadata-Version: 2.4
Name: sipher-lab
Version: 0.1.5
Summary: Classic cipher implementations including Vernam cipher
Home-page: https://github.com/yourusername/sipher-lab
Author: Captain
Author-email: your.email@example.com
License: MIT
Keywords: ciphers cryptography vernam encryption
Platform: any
Classifier: Programming Language :: Python :: 3
Classifier: License :: OSI Approved :: MIT License
Classifier: Operating System :: OS Independent
Requires-Python: >=3.6
Requires-Dist: setuptools>=68.0.0
Dynamic: author
Dynamic: author-email
Dynamic: classifier
Dynamic: description-content-type
Dynamic: home-page
Dynamic: keywords
Dynamic: license
Dynamic: platform
Dynamic: requires-dist
Dynamic: requires-python
Dynamic: summary
